regexfinder/__init__.py
regexfinder/main.py
regexfinder-0.0.3.dist-info/LICENSE
regexfinder-0.0.3.dist-info/METADATA
regexfinder-0.0.3.dist-info/WHEEL
regexfinder-0.0.3.dist-info/top_level.txt
regexfinder-0.0.3.dist-info/RECORD
