Metadata-Version: 2.1
Name: regexfinder
Version: 0.0.3
Author-email: Flori Batusha <floribatusha0@gmail.com>
Project-URL: Check Github, https://github.com/riflosnake/RegexFinder
Classifier: Programming Language :: Python :: 3
Classifier: License :: OSI Approved :: MIT License
Classifier: Operating System :: OS Independent
Requires-Python: >=3.7
License-File: LICENSE
